rebrandly_mcp/__init__.py
rebrandly_mcp/main.py
rebrandly_mcp/models.py
rebrandly_mcp/prompts.py
rebrandly_mcp/server.py
rebrandly_mcp/tools.py
rebrandly_mcp/utils.py
rebrandly_mcp-1.0.0.dist-info/METADATA
rebrandly_mcp-1.0.0.dist-info/WHEEL
rebrandly_mcp-1.0.0.dist-info/entry_points.txt
rebrandly_mcp-1.0.0.dist-info/RECORD
