Metadata-Version: 2.4
Name: rebrandly-mcp
Version: 1.0.0
Summary: MCP Server for rebrandly.com
Author-email: Vimal Paliwal <vimalpaliwal.me@gmail.com>
License-Expression: Apache-2.0
Keywords: mcp,rebrandly,url shortener
Requires-Python: >=3.13
Requires-Dist: httpx>=0.28.1
Requires-Dist: loguru>=0.7.3
Requires-Dist: mcp[cli]>=1.13.1
Requires-Dist: pydantic>=2.11.7
